{
    "name": {
        "id": 1004100000,
        "internal": "Chart",
        "external": "Chart"
    },
    "category": "Tools",
    "version": "1.0.0",
    "requirements": {
        "phpOMS": "1.0.0",
        "phpOMS-db": "1.0.0"
    },
    "creator": {
        "name": "Orange Management",
        "website": "www.spl1nes.com"
    },
    "description": "The administration module.",
    "directory": "Chart",
    "dependencies": {
        "Admin" : "1.0.0",
        "Tools" : "1.0.0"
    },
    "providing": {
        "Navigation": "*"
    },
    "load": [
        {
            "pid": [
                "/backend/chart"
            ],
            "type": 4,
            "for": "Content",
            "file": "Chart",
            "from": "Chart"
        },
        {
            "pid": [
                "/backend"
            ],
            "type": 5,
            "from": "Chart",
            "for": "Navigation",
            "file": "Navigation"
        }
    ]
}
